mklib_manmadegod/__about__.py
mklib_manmadegod/__init__.py
mklib_manmadegod/_logging.py
mklib_manmadegod/_reflection.py
mklib_manmadegod-0.0.6.dist-info/METADATA
mklib_manmadegod-0.0.6.dist-info/WHEEL
mklib_manmadegod-0.0.6.dist-info/licenses/LICENSE.txt
mklib_manmadegod-0.0.6.dist-info/RECORD
